[
  {
    "name": "Organic Cotton T-Shirt",
    "category": "Clothing",
    "price": 19.99,
    "thumbnail": "https://example.com/images/tshirt_thumb.jpg",
    "fullQualityPic": "https://example.com/images/tshirt_full.jpg"
  },
  {
    "name": "Wireless Bluetooth Earbuds",
    "category": "Electronics",
    "price": 49.99,
    "thumbnail": "https://example.com/images/earbuds_thumb.jpg",
    "fullQualityPic": "https://example.com/images/earbuds_full.jpg"
  },
  {
    "name": "Stainless Steel Water Bottle",
    "category": "Accessories",
    "price": 15.99,
    "thumbnail": "https://example.com/images/bottle_thumb.jpg",
    "fullQualityPic": "https://example.com/images/bottle_full.jpg"
  },
  {
    "name": "LED Desk Lamp",
    "category": "Home & Living",
    "price": 24.99,
    "thumbnail": "https://example.com/images/desk_lamp_thumb.jpg",
    "fullQualityPic": "https://example.com/images/desk_lamp_full.jpg"
  },
  {
    "name": "Men's Running Shoes",
    "category": "Footwear",
    "price": 59.99,
    "thumbnail": "https://example.com/images/running_shoes_thumb.jpg",
    "fullQualityPic": "https://example.com/images/running_shoes_full.jpg"
  },
  {
    "name": "Smartphone Holder",
    "category": "Accessories",
    "price": 9.99,
    "thumbnail": "https://example.com/images/phone_holder_thumb.jpg",
    "fullQualityPic": "https://example.com/images/phone_holder_full.jpg"
  },
  {
    "name": "Portable Power Bank",
    "category": "Electronics",
    "price": 29.99,
    "thumbnail": "https://example.com/images/power_bank_thumb.jpg",
    "fullQualityPic": "https://example.com/images/power_bank_full.jpg"
  },
  {
    "name": "Yoga Mat",
    "category": "Sports & Outdoors",
    "price": 20.0,
    "thumbnail": "https://example.com/images/yoga_mat_thumb.jpg",
    "fullQualityPic": "https://example.com/images/yoga_mat_full.jpg"
  },
  {
    "name": "Ceramic Coffee Mug",
    "category": "Home & Kitchen",
    "price": 12.99,
    "thumbnail": "https://example.com/images/coffee_mug_thumb.jpg",
    "fullQualityPic": "https://example.com/images/coffee_mug_full.jpg"
  },
  {
    "name": "Noise-Canceling Headphones",
    "category": "Electronics",
    "price": 89.99,
    "thumbnail": "https://example.com/images/headphones_thumb.jpg",
    "fullQualityPic": "https://example.com/images/headphones_full.jpg"
  }
]
